ib3/__init__.py
ib3/auth.py
ib3/connection.py
ib3/mixins.py
ib3/nick.py
ib3-0.3.0.dist-info/METADATA
ib3-0.3.0.dist-info/WHEEL
ib3-0.3.0.dist-info/licenses/COPYING
ib3-0.3.0.dist-info/RECORD
