Metadata-Version: 2.1
Name: ib3
Version: 0.3.0
Summary: IRC bot framework using mixins to provide common functionality
Project-URL: Homepage, https://python-ib3.readthedocs.io/en/latest/
Project-URL: Bug Tracker, https://github.com/bd808/python-ib3/issues
Project-URL: Source, https://github.com/bd808/python-ib3
Author-email: Bryan Davis <bd808@bd808.com>
License-Expression: GPL-3.0-or-later
License-File: COPYING
Classifier: Development Status :: 4 - Beta
Classifier: Intended Audience :: Developers
Classifier: License :: OSI Approved :: GNU General Public License v3 or later (GPLv3+)
Classifier: Operating System :: OS Independent
Classifier: Programming Language :: Python :: 3
Classifier: Programming Language :: Python :: 3.7
Classifier: Programming Language :: Python :: 3.8
Classifier: Programming Language :: Python :: 3.9
Classifier: Programming Language :: Python :: 3.10
Classifier: Programming Language :: Python :: 3.11
Classifier: Topic :: Communications :: Chat :: Internet Relay Chat
Requires-Python: >=3.7
Requires-Dist: irc>=20.0.0
